{
  "projectMeta": {
    "projectName": "Stringborn Universe",
    "version": "0.1",
    "createdBy": "Violet",
    "description": "A community-driven sci-fi universe with metaphysical domains, species forks, and dynamic planetary zones. Built for 2D gameplay with 3D browser experiences using Three.js.",
    "renderingNotes": {
      "engine": "Three.js (WebGL 2.0)",
      "gpuRequirement": {
        "minimum": "Dedicated GPU with WebGL 2.0 support",
        "recommended": "Modern gaming GPU (e.g., NVIDIA GTX 1060 or equivalent)"
      },
      "mode": "Hybrid 2D/3D browser experience",
      "handoffLogic": "Grid-based planetary cube system with server pass-off per quadrant"
    }
  },

  "species": [/ Silicates, Lanterns, Devan, Humans — as defined earlier /],

  "characterSheetTemplate": {
    "name": "",
    "species": "",
    "stringDomain": "",
    "homeStar": "",
    "homePlanet": "",
    "traits": "",
    "primaryClass": "",
    "level": 1,
    "stats": {
      "strength": 0,
      "intelligence": 0,
      "agility": 0,
      "faith": 0,
      "tech": 0
    },
    "traitBuffs": {
      "passive": [],
      "triggered": []
    },
    "backpack": {
      "items": []
    },
    "equipped": {
      "weapon": null,
      "armor": null,
      "trinket": null
    },
    "enchantments": []
  },

  "talentTrees": {
    "Silicates": {
      "Chronomancer Fork": ["Temporal Glimpse", "Sands of Ages", "Ancestral Echoes"],
      "Crystal Weaver Fork": ["Prismatic Shield", "Shard Summons", "Resonance Cascade"],
      "Era Shifter Fork": ["Timeline Divergence", "Era Conflux", "Chrono-Sovereignty"]
    },
    "Lanterns": {
      "Void Engineer Fork": ["Nullspace Calibration", "Gravity Lens", "Dark Matter Forge"],
      "Tech Sage Fork": ["Data Infusion", "Circuit Mastery", "Singularity Hack"],
      "Umbral Scout Fork": ["Shadow Step", "Night’s Embrace", "Veil Piercer"]
    },
    "Devan": {
      "Covenant Guardian Fork": ["Divine Bulwark", "Sacred Oath", "Celestial Ward"],
      "Faithbinder Fork": ["Spirit Communion", "Blessed Convergence", "Inner Sanctum"],
      "Astral Merchant Fork": ["Star-trade Secrets", "Cosmic Ledger", "Interstellar Pact"]
    },
    "Humans": {
      "Warfire Vanguard Fork": ["Ember Charge", "Iron Pulse", "Battle Cry"],
      "Primal Survivor Fork": ["Adaptive Hide", "Feral Reflex", "Endurance Surge"],
      "Steelborn Tactician Fork": ["Tactical Override", "Armor Sync", "Command Uplink"]
    }
  },

  "zones": {
    "discoveryZone": {
      "zoneName": "Astralara Zenith",
      "description": "A vibrant, lore-rich planetary hub where explorers uncover the secrets of the Devan homeworld.",
      "pointsOfInterest": [
        "Celestial Gardens",
        "Sanctum of Whispers",
        "Astral Market Plaza"
      ]
    },
    "spatialZone": {
      "zoneName": "Umbraxis Rift",
      "description": "A wild, surreal 3D browser experience using Three.js, blending 2D gameplay with spatial distortions.",
      "interactiveElements": [
        "Gravity Wells",
        "Spatial Rifts",
        "Lightwave Platforms"
      ]
    }
  },

  "galacticState": {
    "factions": [
      {
        "name": "Chrono Guild",
        "homeStar": "Alantir",
        "influenceZones": ["Zirion System", "Astralara Periphery"],
        "diplomaticRelations": {
          "Lantern Collective": "allied",
          "Devan Consortium": "neutral",
          "Terran Dominion": "cold"
        }
      },
      {
        "name": "Lantern Collective",
        "homeStar": "Umbraxis",
        "influenceZones": ["Umbraxis Expanse", "Silent Straits"],
        "diplomaticRelations": {
          "Chrono Guild": "allied",
          "Devan Consortium": "neutral",
          "Terran Dominion": "hostile"
        }
      }
    ],
    "resourceDistribution": {
      "quantumCores": {
        "locations": ["Zirion Belt", "Umbraxis Rift", "Earth Outskirts"],
        "scarcity": "rare"
      },
      "exoticCrystals": {
        "locations": ["Seraphon's Gaze", "Celestial Gardens"],
        "scarcity": "uncommon"
      }
    },
    "activeEvents": [
      {
        "eventId": "ev_301",
        "name": "Eclipse of Alantir",
        "description": "A rare alignment causing temporal distortions across the Time String."
      }
    ]
  },

  "planetaryState": {
    "currentGrid": {
      "x": 8,
      "y": 3,
      "z": 2,
      "zoneName": "Celestial Gardens – Quadrant NW",
      "activeServer": "renderserver04"
    },
    "handoffZones": {
      "north": {
        "nextGrid": {"x": 8, "y": 4, "z": 2},
        "zoneName": "Celestial Gardens – Quadrant N",
        "handoffServer": "renderserver05"
      },
      "south": {
        "nextGrid": {"x": 8, "y": 2, "z": 2},
        "zoneName": "Celestial Gardens – Quadrant SW",
        "handoffServer": "renderserver03"
      },
      "east": {
        "nextGrid": {"x": 9, "y": 3, "z": 2},
        "zoneName": "Celestial Gardens – Quadrant NE",
        "handoffServer": "renderserver06"
      },
      "west": {
        "nextGrid": {"x": 7, "y": 3, "z": 2},
        "zoneName": "Celestial Gardens – Quadrant W",
        "handoffServer": "renderserver02"
      }
    }
  }
}